ruptures/__init__.py
ruptures/base.py
ruptures/exceptions.py
ruptures/costs/__init__.py
ruptures/costs/costautoregressive.py
ruptures/costs/costl1.py
ruptures/costs/costl2.py
ruptures/costs/costlinear.py
ruptures/costs/costml.py
ruptures/costs/costnormal.py
ruptures/costs/costrbf.py
ruptures/costs/factory.py
ruptures/datasets/__init__.py
ruptures/datasets/pw_constant.py
ruptures/datasets/pw_linear.py
ruptures/datasets/pw_normal.py
ruptures/datasets/pw_wavy.py
ruptures/detection/__init__.py
ruptures/detection/binseg.py
ruptures/detection/bottomup.py
ruptures/detection/dynp.py
ruptures/detection/greedyar.py
ruptures/detection/greedylinear.py
ruptures/detection/omp.py
ruptures/detection/ompk.py
ruptures/detection/pelt.py
ruptures/detection/sanity_check.py
ruptures/detection/window.py
ruptures/metrics/__init__.py
ruptures/metrics/hamming.py
ruptures/metrics/hausdorff.py
ruptures/metrics/precisionrecall.py
ruptures/metrics/randindex.py
ruptures/metrics/sanity_check.py
ruptures/metrics/timeerror.py
ruptures/show/__init__.py
ruptures/show/display.py
ruptures/utils/__init__.py
ruptures/utils/bnode.py
ruptures/utils/drawbkps.py
ruptures/utils/utils.py
ruptures_headless-1.0a1.post2.dist-info/METADATA
ruptures_headless-1.0a1.post2.dist-info/RECORD
ruptures_headless-1.0a1.post2.dist-info/WHEEL
ruptures_headless-1.0a1.post2.dist-info/top_level.txt
