Metadata-Version: 2.1
Name: ruptures-headless
Version: 1.0a1.post2
Summary: Change point detection for signals, in Python
Home-page: UNKNOWN
Author: Charles Truong, Laurent Oudre, Nicolas Vayatis
Author-email: truong@cmla.ens-cachan.fr
License: BSD License
Download-URL: https://reine.cmla.ens-cachan.fr/c.truong/ruptures/repository/latest/archive.zip
Keywords: change point detection,signal segmentation,computer science,machine learning,kernel methods,time series
Platform: UNKNOWN
Classifier: Programming Language :: Python :: 3
Classifier: Operating System :: OS Independent
Classifier: Topic :: Scientific/Engineering :: Mathematics
Classifier: Intended Audience :: Science/Research
Classifier: License :: OSI Approved :: BSD License
Requires-Python: >=3
Provides-Extra: display
Requires-Dist: numpy
Requires-Dist: scipy
Provides-Extra: display
Requires-Dist: matplotlib; extra == 'display'
